lungs_segmentation/__init__.py
lungs_segmentation/densenet.py
lungs_segmentation/inference.py
lungs_segmentation/pre_trained_models.py
lungs_segmentation/resnet.py
lungs_segmentation/resunets.py
lungs_segmentation/senet.py
lungs_segmentation/unet.py
lungs_segmentation-1.1.2.dist-info/METADATA
lungs_segmentation-1.1.2.dist-info/WHEEL
lungs_segmentation-1.1.2.dist-info/top_level.txt
lungs_segmentation-1.1.2.dist-info/RECORD
