Metadata-Version: 2.1
Name: lungs-segmentation
Version: 1.1.2
Summary: High quality model for lungs segmentation.
Home-page: https://github.com/alimbekovKZ/lungs_segmentation/
Author: Renat Alimbekov, Ivan Vassilenko, Abylaikhan Turlassov
License: MIT
Platform: UNKNOWN
Classifier: License :: OSI Approved :: MIT License
Classifier: Intended Audience :: Developers
Classifier: Intended Audience :: Science/Research
Classifier: Operating System :: OS Independent
Classifier: Programming Language :: Python
Classifier: Programming Language :: Python :: 3
Classifier: Topic :: Software Development :: Libraries
Classifier: Topic :: Software Development :: Libraries :: Python Modules
Requires-Dist: albumentations (==0.5.2)
Requires-Dist: torchvision (==0.8.2)
Requires-Dist: opencv-python (==4.2.0.34)
Requires-Dist: typing (==3.6.4)
Requires-Dist: matplotlib (==3.1.3)
Requires-Dist: setuptools (==49.2.0)
Requires-Dist: torch (==1.7.1)
Requires-Dist: numpy (==1.17.4)
Provides-Extra: test
Requires-Dist: pytest; extra == 'test'
